[
  {
    "book_id": "Pria-Miskin-yang-Kutolong-Ternyata-CEO-7341229572660136961",
    "title": "Pria Miskin yang Kutolong Ternyata CEO",
    "genres": [
      [
        "Identitas Tersembunyi",
        "Romansa",
        "Romansa Urban",
        "Ceo",
        "Serangan balik"
      ],
      {
        "s": "arr"
      }
    ],
    "description": "Lely, putri konglomerat terkaya di Kota Uttar, menyembunyikan identitasnya dan bekerja sebagai pengantar makanan. Dia bertekad untuk hidup mandiri dan menghasilkan uang sendiri. Suatu hari, saat mengantarkan makanan, dia secara tidak sengaja menyelamatkan Rinto, seorang CEO yang tertimpa masalah. Pertemuan ini menjadi awal kisah cinta mereka yang penuh kebahagiaan dan kejutan.",
    "cover_url": "https://cloudins-cdn.insjay.biz.id/media/Ot4Eg3mEFH1U6crG41IguS6zOSQ8kjaybX3B",
    "created_at": "2026-04-24T15:12:16.069Z",
    "episodes": [
      {
        "index": 1,
        "vid": "7341230015322786818",
        "video_url": "https://cloudins-cdn.insjay.biz.id/media/wdcW12QNdAQGwZ4MkNnIQm4Z4rqzXROsioN2",
        "uploaded_at": "2026-04-24T15:12:26.821Z"
      },
      {
        "index": 2,
        "vid": "7341230009488509954",
        "video_url": "https://cloudins-cdn.insjay.biz.id/media/ZpqcZUvG7XyXTzFibrLT2ja58Sxw4yvAXfuv",
        "uploaded_at": "2026-04-24T15:12:27.264Z"
      },
      {
        "index": 3,
        "vid": "7341230024319568897",
        "video_url": "https://cloudins-cdn.insjay.biz.id/media/gJSEcpAJpEyxarOAbM5qZejJJtmc4Wnb6Un2",
        "uploaded_at": "2026-04-24T15:12:28.451Z"
      },
      {
        "index": 4,
        "vid": "7341230020725050369",
        "video_url": "https://cloudins-cdn.insjay.biz.id/media/8kby8SI7CPKO2DU12ugeEJv8EanuWNZZaC7Z",
        "uploaded_at": "2026-04-24T15:12:25.657Z"
      },
      {
        "index": 5,
        "vid": "7341230028291574785",
        "video_url": "https://cloudins-cdn.insjay.biz.id/media/ABaNIQAqAW5THTp5IxYgTf6jbgUnwXaWcgxG",
        "uploaded_at": "2026-04-24T15:12:27.775Z"
      },
      {
        "index": 6,
        "vid": "7341230032032893954",
        "video_url": "https://cloudins-cdn.insjay.biz.id/media/MfmETRJEePdSQY0qIVWGvUHF1noeq5jbdM66",
        "uploaded_at": "2026-04-24T15:12:25.510Z"
      },
      {
        "index": 7,
        "vid": "7341230035367365633",
        "video_url": "https://cloudins-cdn.insjay.biz.id/media/LSYPntV7HXSVnucaLeRiVbheSmWW1AAaqjwL",
        "uploaded_at": "2026-04-24T15:12:26.368Z"
      },
      {
        "index": 8,
        "vid": "7341230046020897794",
        "video_url": "https://cloudins-cdn.insjay.biz.id/media/UCuFIQg90k0EiqsXkK5VgBJoDbAgAxyMWdcn",
        "uploaded_at": "2026-04-24T15:12:56.555Z"
      },
      {
        "index": 9,
        "vid": "7341230049015630850",
        "video_url": "https://cloudins-cdn.insjay.biz.id/media/caCgeJYtDjtYLwrog9QRk1u8taX395Lanm9k",
        "uploaded_at": "2026-04-24T15:12:34.834Z"
      },
      {
        "index": 10,
        "vid": "7341230038206909441",
        "video_url": "https://cloudins-cdn.insjay.biz.id/media/dTPMIBJ47D4EAsmJnOYANJIZIijzTCRQQ9a5",
        "uploaded_at": "2026-04-24T15:12:35.113Z"
      },
      {
        "index": 11,
        "vid": "7341230052471737346",
        "video_url": "https://cloudins-cdn.insjay.biz.id/media/9QBQGLZ1AAQdqaPzzMg1kIdd1gJ4rfioOLog",
        "uploaded_at": "2026-04-24T15:12:36.193Z"
      },
      {
        "index": 12,
        "vid": "7341230058331180033",
        "video_url": "https://cloudins-cdn.insjay.biz.id/media/Zy2KLJLSp9oFVztGsrBu48Dl4DuRlo2ecWVL",
        "uploaded_at": "2026-04-24T15:12:34.028Z"
      },
      {
        "index": 13,
        "vid": "7341230064639413249",
        "video_url": "https://cloudins-cdn.insjay.biz.id/media/8Tm0z6NCWqSYbgxS64h9BWmGLbSCc1BC1Awz",
        "uploaded_at": "2026-04-24T15:12:34.749Z"
      },
      {
        "index": 14,
        "vid": "7341230055139314690",
        "video_url": "https://cloudins-cdn.insjay.biz.id/media/zetaBu4sJpkQ4fZmTeUOHbYhuWhkFtgi5ehB",
        "uploaded_at": "2026-04-24T15:12:33.495Z"
      },
      {
        "index": 15,
        "vid": "7341230061590154242",
        "video_url": "https://cloudins-cdn.insjay.biz.id/media/BAnYqasxnaGYSFUEhcXMIpKQo43IPVnxWXts",
        "uploaded_at": "2026-04-24T15:13:15.388Z"
      },
      {
        "index": 16,
        "vid": "7341230087393512450",
        "video_url": "https://cloudins-cdn.insjay.biz.id/media/SeuaJIYwivoLkteW0pCPn5GPriCVcE5QvuJV",
        "uploaded_at": "2026-04-24T15:13:04.146Z"
      },
      {
        "index": 17,
        "vid": "7341230070637267970",
        "video_url": "https://cloudins-cdn.insjay.biz.id/media/is521N7MAVfu2Gs40q0LQ9YzWK0Zj7j6mI79",
        "uploaded_at": "2026-04-24T15:13:01.740Z"
      },
      {
        "index": 18,
        "vid": "7341230084184869889",
        "video_url": "https://cloudins-cdn.insjay.biz.id/media/GvmJ6khjtRoNEgxhPEgM4YpcjvWVVPYcAm9e",
        "uploaded_at": "2026-04-24T15:13:02.020Z"
      },
      {
        "index": 19,
        "vid": "7341230102954380289",
        "video_url": "https://cloudins-cdn.insjay.biz.id/media/YMv65hVIMa8jS70Eszn2c2iz48aZBKbsqPDd",
        "uploaded_at": "2026-04-24T15:13:01.353Z"
      },
      {
        "index": 20,
        "vid": "7341230067608980481",
        "video_url": "https://cloudins-cdn.insjay.biz.id/media/dfMZcQs2FJJFIsEhUYrwEBTyBx3BYRxxgjwO",
        "uploaded_at": "2026-04-24T15:13:02.673Z"
      },
      {
        "index": 21,
        "vid": "7341230090170141697",
        "video_url": "https://cloudins-cdn.insjay.biz.id/media/MJbEQDcDNSqucAq5vaAJ3bHlLnjT5YYqJOm4",
        "uploaded_at": "2026-04-24T15:13:03.588Z"
      },
      {
        "index": 22,
        "vid": "7341230093051628545",
        "video_url": "https://cloudins-cdn.insjay.biz.id/media/xWeWcLTx7FdNdZZQnZ6UsrXswmwKfYuruSqI",
        "uploaded_at": "2026-04-24T15:13:21.075Z"
      },
      {
        "index": 23,
        "vid": "7341230095996029953",
        "video_url": "https://cloudins-cdn.insjay.biz.id/media/3ScsM9rn9M4KOWcuVQWPVg6AazDBlxvxwfAB",
        "uploaded_at": "2026-04-24T15:13:20.755Z"
      },
      {
        "index": 24,
        "vid": "7341230099351473154",
        "video_url": "https://cloudins-cdn.insjay.biz.id/media/pIBqLTnxj4rWxSr0Z3a5kK7DB1VCUVTTEUS5",
        "uploaded_at": "2026-04-24T15:13:20.036Z"
      },
      {
        "index": 25,
        "vid": "7341230105743592450",
        "video_url": "https://cloudins-cdn.insjay.biz.id/media/RVrrOvBrb2ZpxJ5m9EmeoRHxHixwEVnA6Jvd",
        "uploaded_at": "2026-04-24T15:13:19.711Z"
      },
      {
        "index": 26,
        "vid": "7341230108818017282",
        "video_url": "https://cloudins-cdn.insjay.biz.id/media/nrS3Ut0RNt29l0qViqVILjvdWLN2u3W38o03",
        "uploaded_at": "2026-04-24T15:13:23.320Z"
      },
      {
        "index": 27,
        "vid": "7341230114258029570",
        "video_url": "https://cloudins-cdn.insjay.biz.id/media/OzRIP64ab3AwiEW4J3FeDJmU0PuhCBiJAw99",
        "uploaded_at": "2026-04-24T15:13:21.968Z"
      },
      {
        "index": 28,
        "vid": "7341230111401708545",
        "video_url": "https://cloudins-cdn.insjay.biz.id/media/DsC81hQ0inBHCnzxHYcz3SSd24GrXtQK8OCt",
        "uploaded_at": "2026-04-24T15:13:20.868Z"
      },
      {
        "index": 29,
        "vid": "7341230119496715266",
        "video_url": "https://cloudins-cdn.insjay.biz.id/media/zi895Cm9wn6YCjeWQ9GCmenPtSqrAS6evR03",
        "uploaded_at": "2026-04-24T15:14:01.557Z"
      },
      {
        "index": 30,
        "vid": "7341230117114350594",
        "video_url": "https://cloudins-cdn.insjay.biz.id/media/hqiB0zqiO0y94pNx4fln92pjiGR2VNNJkmwN",
        "uploaded_at": "2026-04-24T15:13:28.235Z"
      },
      {
        "index": 31,
        "vid": "7341230122487254017",
        "video_url": "https://cloudins-cdn.insjay.biz.id/media/i3tAElLAC5dHHSvhMNH7msd0EZsb8eDaT75C",
        "uploaded_at": "2026-04-24T15:13:28.755Z"
      },
      {
        "index": 32,
        "vid": "7341230135510567937",
        "video_url": "https://cloudins-cdn.insjay.biz.id/media/zDWOQKJlti6umkrkkUktFKFQQj8uxwJTIDSm",
        "uploaded_at": "2026-04-24T15:13:27.713Z"
      },
      {
        "index": 33,
        "vid": "7341230127830797313",
        "video_url": "https://cloudins-cdn.insjay.biz.id/media/TtNpwhCe7x89R68b3GoL4uimk9FiV7nsPeiG",
        "uploaded_at": "2026-04-24T15:13:28.588Z"
      },
      {
        "index": 34,
        "vid": "7341230125289049089",
        "video_url": "https://cloudins-cdn.insjay.biz.id/media/k62wDXEKJRRsusyh98eGPaJYnpOPTg7thAiD",
        "uploaded_at": "2026-04-24T15:13:31.834Z"
      },
      {
        "index": 35,
        "vid": "7341230138375277569",
        "video_url": "https://cloudins-cdn.insjay.biz.id/media/s5i8AbovrxRPiQ5Vu8xt0AQXXlHpCzaeOzc3",
        "uploaded_at": "2026-04-24T15:13:28.922Z"
      },
      {
        "index": 36,
        "vid": "7341230145795001346",
        "video_url": "https://cloudins-cdn.insjay.biz.id/media/qvSG8vXNt5SlC3Lmnwz02mdFjfHQ1Z3BWfPp",
        "uploaded_at": "2026-04-24T15:14:06.991Z"
      },
      {
        "index": 37,
        "vid": "7341230148399664129",
        "video_url": "https://cloudins-cdn.insjay.biz.id/media/SjkQlEwAk5HRVPcPi9ejPo7JZPKu7J5xY8tp",
        "uploaded_at": "2026-04-24T15:14:08.154Z"
      },
      {
        "index": 38,
        "vid": "7341230151633472514",
        "video_url": "https://cloudins-cdn.insjay.biz.id/media/GhJm8vBgpNsNkQV3s0Rc3NhmTocagW70MOTO",
        "uploaded_at": "2026-04-24T15:14:08.581Z"
      },
      {
        "index": 39,
        "vid": "7341230154632399873",
        "video_url": "https://cloudins-cdn.insjay.biz.id/media/gBXz1sOBp5KxBHNGmrTXsipkcgShMm2gnlnj",
        "uploaded_at": "2026-04-24T15:14:06.815Z"
      },
      {
        "index": 40,
        "vid": "7341230157371280385",
        "video_url": "https://cloudins-cdn.insjay.biz.id/media/kXOQc15RXGJpUWzUnEbSr1JUXcmGq1blg5zz",
        "uploaded_at": "2026-04-24T15:14:07.213Z"
      },
      {
        "index": 41,
        "vid": "7341230160030469121",
        "video_url": "https://cloudins-cdn.insjay.biz.id/media/0I8FSQ12zVLzBau3hFUloqcKJ2TqzZViKQHC",
        "uploaded_at": "2026-04-24T15:14:08.100Z"
      },
      {
        "index": 42,
        "vid": "7341230176367283202",
        "video_url": "https://cloudins-cdn.insjay.biz.id/media/gODWs06GWVk3bcNJ4bbEeCjwS9n2N3sKTvTz",
        "uploaded_at": "2026-04-24T15:14:06.974Z"
      },
      {
        "index": 43,
        "vid": "7341230163151031298",
        "video_url": "https://cloudins-cdn.insjay.biz.id/media/dRDwq29vn9fFAUu4aXGXLks32akt6PlQyZfi",
        "uploaded_at": "2026-04-24T15:14:14.622Z"
      },
      {
        "index": 44,
        "vid": "7341230169853529089",
        "video_url": "https://cloudins-cdn.insjay.biz.id/media/8vp9XQ3bZFE8P2mQWICj3nkrYRy1Wvrdn18j",
        "uploaded_at": "2026-04-24T15:14:14.831Z"
      },
      {
        "index": 45,
        "vid": "7341230166430977026",
        "video_url": "https://cloudins-cdn.insjay.biz.id/media/ckCJ7do2xZmy7klSZyZjMDMCYJEYcgvA1dnP",
        "uploaded_at": "2026-04-24T15:14:14.633Z"
      },
      {
        "index": 46,
        "vid": "7341230173343190017",
        "video_url": "https://cloudins-cdn.insjay.biz.id/media/FGZ0SjJs7pKOQMjfidXnMTbGygk9MMG4qvCh",
        "uploaded_at": "2026-04-24T15:14:15.208Z"
      },
      {
        "index": 47,
        "vid": "7341230179299101698",
        "video_url": "https://cloudins-cdn.insjay.biz.id/media/4BkAcNsMxnjQxKPfNq2TeZ2aApYEuB1YnrOo",
        "uploaded_at": "2026-04-24T15:14:14.256Z"
      },
      {
        "index": 48,
        "vid": "7341230186899180546",
        "video_url": "https://cloudins-cdn.insjay.biz.id/media/dn6V8EzktT5akUMaM4EhYagThjc3uweYDqyX",
        "uploaded_at": "2026-04-24T15:14:15.097Z"
      },
      {
        "index": 49,
        "vid": "7341230189881330689",
        "video_url": "https://cloudins-cdn.insjay.biz.id/media/FUWqEx4PLe39MuUwWm4CAJsaXFeEdCyMGRAO",
        "uploaded_at": "2026-04-24T15:14:13.765Z"
      },
      {
        "index": 50,
        "vid": "7341230192557296642",
        "video_url": "https://cloudins-cdn.insjay.biz.id/media/mKzt4TUTJoL7LFL9NeP6Mj3EZcFJ0hBMBBqs",
        "uploaded_at": "2026-04-24T15:14:22.548Z"
      },
      {
        "index": 51,
        "vid": "7341230195212291073",
        "video_url": "https://cloudins-cdn.insjay.biz.id/media/eqAm4krX0bC3CRB6qZ0pWnmWcLWN8SpiSMeZ",
        "uploaded_at": "2026-04-24T15:14:21.402Z"
      },
      {
        "index": 52,
        "vid": "7341230201210145794",
        "video_url": "https://cloudins-cdn.insjay.biz.id/media/I7L4LhA5joLcf7i9rqg22BtXlIyPg1bRjhg9",
        "uploaded_at": "2026-04-24T15:14:22.481Z"
      },
      {
        "index": 53,
        "vid": "7341230198391573506",
        "video_url": "https://cloudins-cdn.insjay.biz.id/media/6QZUWz6dytc6pTC1BxkS78YHjqNsdSzImW0c",
        "uploaded_at": "2026-04-24T15:14:20.546Z"
      },
      {
        "index": 54,
        "vid": "7341230204154547201",
        "video_url": "https://cloudins-cdn.insjay.biz.id/media/jq97lndhImKzMEyCEuqHaBp1CKCxvRttzEOb",
        "uploaded_at": "2026-04-24T15:14:22.224Z"
      },
      {
        "index": 55,
        "vid": "7341230207673568257",
        "video_url": "https://cloudins-cdn.insjay.biz.id/media/ADyNALwPlJpzyx8DP01sUQ86vis05bap2iu0",
        "uploaded_at": "2026-04-24T15:14:21.584Z"
      },
      {
        "index": 56,
        "vid": "7341230210290813953",
        "video_url": "https://cloudins-cdn.insjay.biz.id/media/tm2J5S7ozIGOJcfAr2e368WAeXpEsHpdrMYi",
        "uploaded_at": "2026-04-24T15:14:19.733Z"
      },
      {
        "index": 57,
        "vid": "7341230220604607489",
        "video_url": "https://cloudins-cdn.insjay.biz.id/media/Np1OidtyOyvQHWive8v9B5mypsjsGlLf46iU",
        "uploaded_at": "2026-04-24T15:14:27.638Z"
      },
      {
        "index": 58,
        "vid": "7341230213210049538",
        "video_url": "https://cloudins-cdn.insjay.biz.id/media/nWUT9xsgZSTMBi16FzsPIZWeR4bqDNkA5xYv",
        "uploaded_at": "2026-04-24T15:14:27.293Z"
      },
      {
        "index": 59,
        "vid": "7341230235293060097",
        "video_url": "https://cloudins-cdn.insjay.biz.id/media/bLAbWE7PbZgb9Rnxa6Vv7AlwpiFfCaZVI8zO",
        "uploaded_at": "2026-04-24T15:14:27.826Z"
      },
      {
        "index": 60,
        "vid": "7341230232742923266",
        "video_url": "https://cloudins-cdn.insjay.biz.id/media/AOkNlTVzrKwfPiH5nju5jtXTghbBzOzTQpHt",
        "uploaded_at": "2026-04-24T15:14:28.151Z"
      },
      {
        "index": 61,
        "vid": "7341230237939665922",
        "video_url": "https://cloudins-cdn.insjay.biz.id/media/a5gfaJLL5BEDTLrtT3qupEuY58jVQfoMxAfh",
        "uploaded_at": "2026-04-24T15:14:31.318Z"
      },
      {
        "index": 62,
        "vid": "7341230240728878081",
        "video_url": "https://cloudins-cdn.insjay.biz.id/media/QeN6Mo2pF6DOtBiBCLuzzbh5k17gzVv3g5by",
        "uploaded_at": "2026-04-24T15:14:28.303Z"
      },
      {
        "index": 63,
        "vid": "7341230243513895937",
        "video_url": "https://cloudins-cdn.insjay.biz.id/media/IKCeUdjmOIk2QZaxm2m7wkQZADAw1bIMFnE2",
        "uploaded_at": "2026-04-24T15:14:28.756Z"
      },
      {
        "index": 64,
        "vid": "7341230273033407490",
        "video_url": "https://cloudins-cdn.insjay.biz.id/media/Tf9t1wOGPs1sWqDMEJgNKsSnMPyardSzmy5z",
        "uploaded_at": "2026-04-24T15:14:36.722Z"
      },
      {
        "index": 65,
        "vid": "7341230246353439746",
        "video_url": "https://cloudins-cdn.insjay.biz.id/media/uIlm2zds4cFJKDbyb2QUInUVaRQkdi1Ac6cD",
        "uploaded_at": "2026-04-24T15:14:38.006Z"
      },
      {
        "index": 66,
        "vid": "7341230251558571010",
        "video_url": "https://cloudins-cdn.insjay.biz.id/media/j5gN9oHPtsxya6tpfGR9MKQQT6fz85uSGQof",
        "uploaded_at": "2026-04-24T15:14:37.361Z"
      },
      {
        "index": 67,
        "vid": "7341230249109097473",
        "video_url": "https://cloudins-cdn.insjay.biz.id/media/tFMUtPSxfK8TrNG1t3tZitFuTnp9FnuTDpCY",
        "uploaded_at": "2026-04-24T15:14:36.861Z"
      },
      {
        "index": 68,
        "vid": "7341230254347783169",
        "video_url": "https://cloudins-cdn.insjay.biz.id/media/Z4hfi8L0DMoM54NTCXW4MfxgqPZ1kK6e9lYX",
        "uploaded_at": "2026-04-24T15:14:37.350Z"
      },
      {
        "index": 69,
        "vid": "7341230259670354946",
        "video_url": "https://cloudins-cdn.insjay.biz.id/media/udrLm6tQPn35K5piuG4UgT0NkLDjz3Mlb8Nx",
        "uploaded_at": "2026-04-24T15:14:37.937Z"
      },
      {
        "index": 70,
        "vid": "7341230257023749122",
        "video_url": "https://cloudins-cdn.insjay.biz.id/media/RkVFcx2zQzDz3mnYHRmhCk3BXKHAOqqeVzfe",
        "uploaded_at": "2026-04-24T15:14:36.753Z"
      },
      {
        "index": 71,
        "vid": "7341230262790917121",
        "video_url": "https://cloudins-cdn.insjay.biz.id/media/BVx6XHFReSDcoJnEdGufmGmzdneL3C615KOX",
        "uploaded_at": "2026-04-24T15:14:44.453Z"
      },
      {
        "index": 72,
        "vid": "7341230265609489409",
        "video_url": "https://cloudins-cdn.insjay.biz.id/media/R8QioXF3MJyWx8y6OU6K09T9vZDKXBSgfTgK",
        "uploaded_at": "2026-04-24T15:14:42.970Z"
      },
      {
        "index": 73,
        "vid": "7341230275742927873",
        "video_url": "https://cloudins-cdn.insjay.biz.id/media/LtvvpwKVnmPwvtTSC3phNZpLR5MmQW0Kz4xO",
        "uploaded_at": "2026-04-24T15:14:43.524Z"
      },
      {
        "index": 74,
        "vid": "7341230278339202049",
        "video_url": "https://cloudins-cdn.insjay.biz.id/media/nfjgm9W9oPTzHTn4QErUoKDan2vCsC6OD5NT",
        "uploaded_at": "2026-04-24T15:14:44.163Z"
      },
      {
        "index": 75,
        "vid": "7341230287721860098",
        "video_url": "https://cloudins-cdn.insjay.biz.id/media/mxBRjwxlt4XNZmEkhtONiDp5SyjFJsS3M4XM",
        "uploaded_at": "2026-04-24T15:14:42.415Z"
      },
      {
        "index": 76,
        "vid": "7341230281182940162",
        "video_url": "https://cloudins-cdn.insjay.biz.id/media/Pax211XxgtdxWmPldi0aa8CI5vUA9NTnAgy3",
        "uploaded_at": "2026-04-24T15:14:42.337Z"
      },
      {
        "index": 77,
        "vid": "7341230284362222593",
        "video_url": "https://cloudins-cdn.insjay.biz.id/media/RW55qe4lIkjZ3zz0hWGKYjNNiLtG5kGHepte",
        "uploaded_at": "2026-04-24T15:14:43.157Z"
      },
      {
        "index": 78,
        "vid": "7341230290653678594",
        "video_url": "https://cloudins-cdn.insjay.biz.id/media/7BcPvjRDIhZd1XFyGnlCltI3v4mjtE1639jT",
        "uploaded_at": "2026-04-24T15:14:50.292Z"
      },
      {
        "index": 79,
        "vid": "7341230296185965570",
        "video_url": "https://cloudins-cdn.insjay.biz.id/media/VQvEiJ8EY8Fx3bz220BwcWynhr3xr7unQ7SB",
        "uploaded_at": "2026-04-24T15:14:51.255Z"
      },
      {
        "index": 80,
        "vid": "7341230293614857218",
        "video_url": "https://cloudins-cdn.insjay.biz.id/media/KHwOoTWOLKXVVXcmogZI5AUBGUqkyBsSpnYg",
        "uploaded_at": "2026-04-24T15:14:49.172Z"
      }
    ]
  },
  {
    "book_id": "Tolak-Sistem-Hadiah-7631400944575450165",
    "title": "Tolak Sistem Hadiah",
    "genres": [
      [
        "Harem",
        "Pemeran Utama Pria",
        "Imajinasi Perkotaan",
        "Serangan balik",
        "Sistem"
      ],
      {
        "s": "arr"
      }
    ],
    "description": "Rizky Pratama, mahasiswa miskin, terikat sistem hadiah yang menjanjikan kemewahan jika ia memenangkan hati banyak wanita. Di tengah kebingungan dan kekosongan materi, ia menyadari kepalsuan sistem tersebut. Rizky akhirnya memilih melepas semua hadiah demi mengejar cinta tulus Putri Cahaya dan kebahagiaan sejati.",
    "cover_url": "https://cloudins-cdn.insjay.biz.id/media/kpbqNNy7CFrA54HI8K9BAzDH0fPrGVhkf5im",
    "created_at": "2026-04-24T15:27:44.317Z",
    "episodes": [
      {
        "index": 1,
        "vid": "7631403979775151109",
        "video_url": "https://cloudins-cdn.insjay.biz.id/media/4QqU1MeEZTNzcYUA1Xo1l7LeGaOq9dRzruOp",
        "uploaded_at": "2026-04-24T15:27:53.542Z"
      },
      {
        "index": 2,
        "vid": "7631403983109622789",
        "video_url": "https://cloudins-cdn.insjay.biz.id/media/PWwzLCK9sKhd9ub3dQQUv42LmikUujC3GtAt",
        "uploaded_at": "2026-04-24T15:27:55.898Z"
      },
      {
        "index": 3,
        "vid": "7631403986267933749",
        "video_url": "https://cloudins-cdn.insjay.biz.id/media/J1SFr5NLE03kgvJnrrxbZnAtSzJi94BaFdqE",
        "uploaded_at": "2026-04-24T15:27:54.937Z"
      },
      {
        "index": 4,
        "vid": "7631403989501742085",
        "video_url": "https://cloudins-cdn.insjay.biz.id/media/VdCdF1sIEaboLrgIWeOeD8ptzkhNtw1XlMP6",
        "uploaded_at": "2026-04-24T15:27:53.237Z"
      },
      {
        "index": 5,
        "vid": "7631403992760716341",
        "video_url": "https://cloudins-cdn.insjay.biz.id/media/MOIjRqVY8joIkCyh5qPkRwNHH51C9ti8DQDY",
        "uploaded_at": "2026-04-24T15:27:54.646Z"
      },
      {
        "index": 6,
        "vid": "7631403995952581637",
        "video_url": "https://cloudins-cdn.insjay.biz.id/media/PFskdINVluJsd4y9QEMgzuS8ayXrosZBYw9b",
        "uploaded_at": "2026-04-24T15:27:54.580Z"
      },
      {
        "index": 7,
        "vid": "7631403998909566005",
        "video_url": "https://cloudins-cdn.insjay.biz.id/media/i2cpIGfa2wnBE9ex86OvO1f9UpMTggrFZsor",
        "uploaded_at": "2026-04-24T15:27:53.793Z"
      },
      {
        "index": 8,
        "vid": "7631404001665240069",
        "video_url": "https://cloudins-cdn.insjay.biz.id/media/V3BTmm76vKbMfyDQ4Pt7Hdb64VZV9hYqAC0Q",
        "uploaded_at": "2026-04-24T15:28:02.691Z"
      },
      {
        "index": 9,
        "vid": "7631404004936780853",
        "video_url": "https://cloudins-cdn.insjay.biz.id/media/F5lQHlVCb32dDPhErYDJH18AX56aTYJpAyux",
        "uploaded_at": "2026-04-24T15:28:03.291Z"
      },
      {
        "index": 10,
        "vid": "7631404008720059397",
        "video_url": "https://cloudins-cdn.insjay.biz.id/media/zdFIfTrysuODOnlsKrlvuLYdMrEns6CV5gpc",
        "uploaded_at": "2026-04-24T15:28:04.182Z"
      },
      {
        "index": 11,
        "vid": "7631404012130012165",
        "video_url": "https://cloudins-cdn.insjay.biz.id/media/o4AM6APJcZDjhX94pEZX9siURekuZ0ULrT2n",
        "uploaded_at": "2026-04-24T15:28:01.821Z"
      },
      {
        "index": 12,
        "vid": "7631404015460289589",
        "video_url": "https://cloudins-cdn.insjay.biz.id/media/rRoeljCAPO8f4yzoYtChxYAIf7dRRfSmTbBo",
        "uploaded_at": "2026-04-24T15:28:02.318Z"
      },
      {
        "index": 13,
        "vid": "7631404018715069445",
        "video_url": "https://cloudins-cdn.insjay.biz.id/media/Op2YLKGsqdAmnclBtdWwUP0rsGboA578AKse",
        "uploaded_at": "2026-04-24T15:28:02.492Z"
      },
      {
        "index": 14,
        "vid": "7631404021713996805",
        "video_url": "https://cloudins-cdn.insjay.biz.id/media/enUlEy98Nyj3oNkHWDiAuGy73w7dSpN32ym8",
        "uploaded_at": "2026-04-24T15:28:04.285Z"
      },
      {
        "index": 15,
        "vid": "7631404024314465333",
        "video_url": "https://cloudins-cdn.insjay.biz.id/media/B4Cqy1s35bFYsgqTjXu5CxKGJUvoctnk8g8b",
        "uploaded_at": "2026-04-24T15:28:10.652Z"
      },
      {
        "index": 16,
        "vid": "7631404027082705973",
        "video_url": "https://cloudins-cdn.insjay.biz.id/media/SBwKPGmi4nwO2daCb3wZBFh43BKhD5r1ONT4",
        "uploaded_at": "2026-04-24T15:28:11.141Z"
      },
      {
        "index": 17,
        "vid": "7631404029959998469",
        "video_url": "https://cloudins-cdn.insjay.biz.id/media/x7F9V05vBFclrd04jFERgpckamVZgb1zeSXf",
        "uploaded_at": "2026-04-24T15:28:11.830Z"
      },
      {
        "index": 18,
        "vid": "7631404033223183365",
        "video_url": "https://cloudins-cdn.insjay.biz.id/media/vhPB1ohcihdDNxnsuMDUjRyi50av6pewEoJU",
        "uploaded_at": "2026-04-24T15:28:10.034Z"
      },
      {
        "index": 19,
        "vid": "7631404035999812613",
        "video_url": "https://cloudins-cdn.insjay.biz.id/media/uGIYkIpCDXexGDAgjC45ICZBAMUSMEmkwrbH",
        "uploaded_at": "2026-04-24T15:28:10.130Z"
      },
      {
        "index": 20,
        "vid": "7631404038898076677",
        "video_url": "https://cloudins-cdn.insjay.biz.id/media/HaMNShhiWR1ZMaanM6HdntStMcOftvAI3Hbh",
        "uploaded_at": "2026-04-24T15:28:11.312Z"
      },
      {
        "index": 21,
        "vid": "7631404042182200325",
        "video_url": "https://cloudins-cdn.insjay.biz.id/media/Fz7TucCvqsk3zxKodkxAaZELsTEKwkDxnHX9",
        "uploaded_at": "2026-04-24T15:28:14.287Z"
      },
      {
        "index": 22,
        "vid": "7631404045713804341",
        "video_url": "https://cloudins-cdn.insjay.biz.id/media/BCY4NmfZlzIE1osLnYzwz0v90bi7naTkryX5",
        "uploaded_at": "2026-04-24T15:28:21.698Z"
      },
      {
        "index": 23,
        "vid": "7631404048972778549",
        "video_url": "https://cloudins-cdn.insjay.biz.id/media/XDnyR0d3j4ZOFMfdYje0eNyTJyoygUC1qKJG",
        "uploaded_at": "2026-04-24T15:28:23.836Z"
      },
      {
        "index": 24,
        "vid": "7631404051866848309",
        "video_url": "https://cloudins-cdn.insjay.biz.id/media/HDov8zU9YWF6CJmkxKZmfG8ytsfOjLFQy8Ai",
        "uploaded_at": "2026-04-24T15:28:20.512Z"
      },
      {
        "index": 25,
        "vid": "7631404054593145861",
        "video_url": "https://cloudins-cdn.insjay.biz.id/media/zisr7v8e90M4xiGij2RLK7qHQ3p3aky7nUm4",
        "uploaded_at": "2026-04-24T15:28:21.268Z"
      },
      {
        "index": 26,
        "vid": "7631404057977949237",
        "video_url": "https://cloudins-cdn.insjay.biz.id/media/OBaqbeQP4XAEtQHP2R9QcfLv22trpf2CNCmH",
        "uploaded_at": "2026-04-24T15:28:26.071Z"
      },
      {
        "index": 27,
        "vid": "7631404060918156341",
        "video_url": "https://cloudins-cdn.insjay.biz.id/media/BhjvKEQ0Q40C4icXJIwcWwvfDOlHBgg6Jjm1",
        "uploaded_at": "2026-04-24T15:28:21.474Z"
      },
      {
        "index": 28,
        "vid": "7631404064089066501",
        "video_url": "https://cloudins-cdn.insjay.biz.id/media/wUue3WuaAIrRIHwl4ytoLzsaN9g007HC3FnF",
        "uploaded_at": "2026-04-24T15:28:19.788Z"
      },
      {
        "index": 29,
        "vid": "7631404067104754741",
        "video_url": "https://cloudins-cdn.insjay.biz.id/media/cuAdzQIeXne67GN6hLoUS9nxUK49ykzyIXNp",
        "uploaded_at": "2026-04-24T15:28:34.561Z"
      },
      {
        "index": 30,
        "vid": "7631404070116264965",
        "video_url": "https://cloudins-cdn.insjay.biz.id/media/QkzlhEZy3RuMRTkOAOMOAOiu6I7lATvRGOGN",
        "uploaded_at": "2026-04-24T15:28:33.050Z"
      },
      {
        "index": 31,
        "vid": "7631404073010334725",
        "video_url": "https://cloudins-cdn.insjay.biz.id/media/ui8wb8WDUOIQEbhY6kxH4pE42DygKYy188qE",
        "uploaded_at": "2026-04-24T15:28:40.551Z"
      },
      {
        "index": 32,
        "vid": "7631404076432886789",
        "video_url": "https://cloudins-cdn.insjay.biz.id/media/vm6k5G0RT8WBxWubfig9RCpLTzOd6bSgrJWK",
        "uploaded_at": "2026-04-24T15:28:33.382Z"
      },
      {
        "index": 33,
        "vid": "7631404080744631349",
        "video_url": "https://cloudins-cdn.insjay.biz.id/media/dT2aC0ErLzyAqRKXtFqFfOSoCT6oWTU5XHqt",
        "uploaded_at": "2026-04-24T15:28:32.162Z"
      },
      {
        "index": 34,
        "vid": "7631404084653722677",
        "video_url": "https://cloudins-cdn.insjay.biz.id/media/ZPqZZpcAY4Bn7XfIZxwFXL0RVu5Dkn65XYvb",
        "uploaded_at": "2026-04-24T15:28:35.697Z"
      },
      {
        "index": 35,
        "vid": "7631404087312911365",
        "video_url": "https://cloudins-cdn.insjay.biz.id/media/9JQ0KEQWEWcOOmQjZXqBfN9RrJhh9wqSQpiI",
        "uploaded_at": "2026-04-24T15:28:31.957Z"
      },
      {
        "index": 36,
        "vid": "7631404090341215237",
        "video_url": "https://cloudins-cdn.insjay.biz.id/media/0fQsHIw48cc7XFyidZKKcZIePtsldwRfAlO8",
        "uploaded_at": "2026-04-24T15:28:52.955Z"
      },
      {
        "index": 37,
        "vid": "7631404093323348997",
        "video_url": "https://cloudins-cdn.insjay.biz.id/media/p2K4UNIRa6rNaRk2bUkBZkNRF6Cey57hcA9d",
        "uploaded_at": "2026-04-24T15:28:48.259Z"
      },
      {
        "index": 38,
        "vid": "7631404096246795269",
        "video_url": "https://cloudins-cdn.insjay.biz.id/media/i8v9VA19NAQ6PxbBwTuUiCCWGFzfH4nQdUZ8",
        "uploaded_at": "2026-04-24T15:28:53.123Z"
      },
      {
        "index": 39,
        "vid": "7631404099069545525",
        "video_url": "https://cloudins-cdn.insjay.biz.id/media/YzPpEcJn296caUKiYGLSF2advNeNVPB4MsxT",
        "uploaded_at": "2026-04-24T15:28:46.383Z"
      },
      {
        "index": 40,
        "vid": "7631404101904894981",
        "video_url": "https://cloudins-cdn.insjay.biz.id/media/obW1lAp1ouppxXmTgYHwjWautwqjvvSUUbKh",
        "uploaded_at": "2026-04-24T15:28:47.174Z"
      },
      {
        "index": 41,
        "vid": "7631404104505363509",
        "video_url": "https://cloudins-cdn.insjay.biz.id/media/gWCxX77Xb0BAAdhWXvKACB2q0H5u0H63eV0X",
        "uploaded_at": "2026-04-24T15:28:46.219Z"
      },
      {
        "index": 42,
        "vid": "7631404107579788341",
        "video_url": "https://cloudins-cdn.insjay.biz.id/media/fFaPJwpP3VsJ3tWER50IBBREuUyDXU5GtggR",
        "uploaded_at": "2026-04-24T15:29:18.223Z"
      },
      {
        "index": 43,
        "vid": "7631404111077837877",
        "video_url": "https://cloudins-cdn.insjay.biz.id/media/C5REYsqSHEJlJaPeg7lkxCuZMVqUHOAlsGc9",
        "uploaded_at": "2026-04-24T15:29:23.977Z"
      },
      {
        "index": 44,
        "vid": "7631404114047405109",
        "video_url": "https://cloudins-cdn.insjay.biz.id/media/1CgMzGg1LsM6cTzFm15oEyLvcvbAHLHrIgxu",
        "uploaded_at": "2026-04-24T15:29:24.193Z"
      },
      {
        "index": 45,
        "vid": "7631404117365099573",
        "video_url": "https://cloudins-cdn.insjay.biz.id/media/XRJIufAJE6YaoD8qpxZc1IwSEiWZQojs5iOn",
        "uploaded_at": "2026-04-24T15:29:24.276Z"
      },
      {
        "index": 46,
        "vid": "7631404120468884533",
        "video_url": "https://cloudins-cdn.insjay.biz.id/media/ZLD3aN6WXZa3bvkrvZXsxeqJej3RKTESP2XC",
        "uploaded_at": "2026-04-24T15:29:22.903Z"
      },
      {
        "index": 47,
        "vid": "7631404123396508677",
        "video_url": "https://cloudins-cdn.insjay.biz.id/media/I4regOBi79umE6UePm1KflfanAt9LK2YHwRt",
        "uploaded_at": "2026-04-24T15:29:25.280Z"
      },
      {
        "index": 48,
        "vid": "7631404126324132869",
        "video_url": "https://cloudins-cdn.insjay.biz.id/media/SydJHvURmZbn8ihOX7EMtXwan27heTq6AQnl",
        "uploaded_at": "2026-04-24T15:29:26.711Z"
      },
      {
        "index": 49,
        "vid": "7631404129025281029",
        "video_url": "https://cloudins-cdn.insjay.biz.id/media/1VmzKkR55SpeaIYBTGIlHM2SV0c5AhFv1T5P",
        "uploaded_at": "2026-04-24T15:29:26.512Z"
      },
      {
        "index": 50,
        "vid": "7631404136474348549",
        "video_url": "https://cloudins-cdn.insjay.biz.id/media/wj2F5Gn2DeBEwyZU5aIsGHWKp5yx1zoIaGSJ",
        "uploaded_at": "2026-04-24T15:29:33.085Z"
      },
      {
        "index": 51,
        "vid": "7631404139708156981",
        "video_url": "https://cloudins-cdn.insjay.biz.id/media/iLhyd3J7vrT4tg5r57NsnT2zoVn2W56s0Ypd",
        "uploaded_at": "2026-04-24T15:29:32.602Z"
      },
      {
        "index": 52,
        "vid": "7631404142438665221",
        "video_url": "https://cloudins-cdn.insjay.biz.id/media/166Z9yRMBH4Ppiup7IH78nj61ojke5c8h94o",
        "uploaded_at": "2026-04-24T15:29:40.659Z"
      },
      {
        "index": 53,
        "vid": "7631404145336912949",
        "video_url": "https://cloudins-cdn.insjay.biz.id/media/TpzTxbb7fUWnyarXvNYAAn43skla4cX3Xj5N",
        "uploaded_at": "2026-04-24T15:29:32.312Z"
      },
      {
        "index": 54,
        "vid": "7631404148230999045",
        "video_url": "https://cloudins-cdn.insjay.biz.id/media/l3SMOLMHD1cyxT8lTTVRBfkedSsabQ0QklPK",
        "uploaded_at": "2026-04-24T15:29:32.477Z"
      },
      {
        "index": 55,
        "vid": "7631404150927920181",
        "video_url": "https://cloudins-cdn.insjay.biz.id/media/KcPGGOo2N0YS8RQyefcvIwH8VMYz2E6odSga",
        "uploaded_at": "2026-04-24T15:29:33.831Z"
      },
      {
        "index": 56,
        "vid": "7631404153528388661",
        "video_url": "https://cloudins-cdn.insjay.biz.id/media/38clVwiR0JpZXwVLg6191mqBA4Gm4lDkGY3B",
        "uploaded_at": "2026-04-24T15:29:34.006Z"
      },
      {
        "index": 57,
        "vid": "7631404156254686261",
        "video_url": "https://cloudins-cdn.insjay.biz.id/media/Ge5FgM4veyPjAR9BKA01KtxJLoMUWqai4Xxb",
        "uploaded_at": "2026-04-24T15:29:46.759Z"
      },
      {
        "index": 58,
        "vid": "7631404159077469189",
        "video_url": "https://cloudins-cdn.insjay.biz.id/media/TlHnHZkVGtFFWlzRfF9iP3lyeYdbJ2uvZCkj",
        "uploaded_at": "2026-04-24T15:29:47.024Z"
      },
      {
        "index": 59,
        "vid": "7631404161732463621",
        "video_url": "https://cloudins-cdn.insjay.biz.id/media/cskp4uFQrPBtNuNXGrymXd9HoF7Yp6fR1466",
        "uploaded_at": "2026-04-24T15:29:46.734Z"
      },
      {
        "index": 60,
        "vid": "7631404164693625909",
        "video_url": "https://cloudins-cdn.insjay.biz.id/media/hQf8V66ZG60CkHWQX81tCZJ3JpJ5n1ucOzl2",
        "uploaded_at": "2026-04-24T15:29:57.503Z"
      },
      {
        "index": 61,
        "vid": "7631404167826770997",
        "video_url": "https://cloudins-cdn.insjay.biz.id/media/fdpEsq86cRRAC3igtfueTsl63GNxje8OYwZT",
        "uploaded_at": "2026-04-24T15:29:48.555Z"
      },
      {
        "index": 62,
        "vid": "7631404170758589493",
        "video_url": "https://cloudins-cdn.insjay.biz.id/media/1iy7DNGKCURV9hBTwggOGrUhqDqhU3Cj0DiY",
        "uploaded_at": "2026-04-24T15:29:47.318Z"
      },
      {
        "index": 63,
        "vid": "7631404173916916741",
        "video_url": "https://cloudins-cdn.insjay.biz.id/media/ZW09YSIYEy86hObUglel8udzkpWfwGL76eTX",
        "uploaded_at": "2026-04-24T15:29:47.600Z"
      },
      {
        "index": 64,
        "vid": "7631404176513174581",
        "video_url": "https://cloudins-cdn.insjay.biz.id/media/NHs8Qtw1lAe9tbwncvUxwo5mCwiOeeFCjc6p",
        "uploaded_at": "2026-04-24T15:30:04.727Z"
      },
      {
        "index": 65,
        "vid": "7631404179499519029",
        "video_url": "https://cloudins-cdn.insjay.biz.id/media/jXwf0NA93SK66gc7ByltjEb94II56moNZsfQ",
        "uploaded_at": "2026-04-24T15:30:10.794Z"
      },
      {
        "index": 66,
        "vid": "7631404189628779525",
        "video_url": "https://cloudins-cdn.insjay.biz.id/media/Isexv6S8PWVRE69GmxXWMq7xokGTvaltpzbf",
        "uploaded_at": "2026-04-24T15:30:04.006Z"
      },
      {
        "index": 67,
        "vid": "7631404192426363957",
        "video_url": "https://cloudins-cdn.insjay.biz.id/media/o5VI70Jz2shstaEEmOcUpiN53ZjKOgJTzedt",
        "uploaded_at": "2026-04-24T15:30:28.143Z"
      },
      {
        "index": 68,
        "vid": "7631404195278490629",
        "video_url": "https://cloudins-cdn.insjay.biz.id/media/zP2Pea8cjtHPlV5K3kS0pRfBGqgPxcOtSPV1",
        "uploaded_at": "2026-04-24T15:30:03.732Z"
      },
      {
        "index": 69,
        "vid": "7631404202035514421",
        "video_url": "https://cloudins-cdn.insjay.biz.id/media/7XQMwWhQxFi4dsU2pgRBPY9vgx5wcKy0Qp5E",
        "uploaded_at": "2026-04-24T15:30:29.048Z"
      },
      {
        "index": 70,
        "vid": "7631404204711496709",
        "video_url": "https://cloudins-cdn.insjay.biz.id/media/C1oePOJOynEqXt2zYi7XmYpptIquOa5BmIbp",
        "uploaded_at": "2026-04-24T15:30:04.345Z"
      },
      {
        "index": 71,
        "vid": "7631404207551024181",
        "video_url": "https://cloudins-cdn.insjay.biz.id/media/VCiidRDJbW7YpsZJqHpGuTwmbiGadHrqkOF0",
        "uploaded_at": "2026-04-24T15:30:39.809Z"
      },
      {
        "index": 72,
        "vid": "7631404210533174325",
        "video_url": "https://cloudins-cdn.insjay.biz.id/media/MiNJid14bSBWWffmjTvsuKCyVm9m7lD9mX4V",
        "uploaded_at": "2026-04-24T15:30:40.200Z"
      },
      {
        "index": 73,
        "vid": "7631404214488419333",
        "video_url": "https://cloudins-cdn.insjay.biz.id/media/jmdA3Fqbsk3dBTyZeO2rjypqyqmgmtyViE0D",
        "uploaded_at": "2026-04-24T15:30:37.487Z"
      },
      {
        "index": 74,
        "vid": "7631404217994841093",
        "video_url": "https://cloudins-cdn.insjay.biz.id/media/oGHspqqf1rHyraOE7bEFqYBuxbXrmLNy6eGZ",
        "uploaded_at": "2026-04-24T15:30:40.840Z"
      },
      {
        "index": 75,
        "vid": "7631404220721138693",
        "video_url": "https://cloudins-cdn.insjay.biz.id/media/JeekaAqDe31t7jgRlMXWd96xd7Dbjafzh2Ep",
        "uploaded_at": "2026-04-24T15:30:40.228Z"
      },
      {
        "index": 76,
        "vid": "7631404223535533061",
        "video_url": "https://cloudins-cdn.insjay.biz.id/media/a0IthvrR0p1WQM3QNwdzknt24WnZuW3hfjdT",
        "uploaded_at": "2026-04-24T15:30:37.489Z"
      },
      {
        "index": 77,
        "vid": "7631404226173750277",
        "video_url": "https://cloudins-cdn.insjay.biz.id/media/f9gZQG3XCAfDboEAFNMjh8xnUINJWWDwallr",
        "uploaded_at": "2026-04-24T15:30:41.502Z"
      },
      {
        "index": 78,
        "vid": "7631404229118135349",
        "video_url": "https://cloudins-cdn.insjay.biz.id/media/w5AbX0gcK8R0OGwXieOLictreadsWRVL6MTb",
        "uploaded_at": "2026-04-24T15:30:50.390Z"
      },
      {
        "index": 79,
        "vid": "7631404231802489909",
        "video_url": "https://cloudins-cdn.insjay.biz.id/media/8VjnJAr3dwJswzb9G6X1b1rdqjCYNixlRY7i",
        "uploaded_at": "2026-04-24T15:30:50.578Z"
      },
      {
        "index": 80,
        "vid": "7631404234390391813",
        "video_url": "https://cloudins-cdn.insjay.biz.id/media/fdyCoCrIhr6Iu1wWMoCCtunutcZiqzeBCBZL",
        "uploaded_at": "2026-04-24T15:30:52.161Z"
      },
      {
        "index": 81,
        "vid": "7631404237376719925",
        "video_url": "https://cloudins-cdn.insjay.biz.id/media/jeGIyfZvXCU503hL0gqxvH1TkLS78kKLQ9Ad",
        "uploaded_at": "2026-04-24T15:30:49.716Z"
      },
      {
        "index": 82,
        "vid": "7631404241080290357",
        "video_url": "https://cloudins-cdn.insjay.biz.id/media/zhzKCaFkqnD7O7vdOD1psK6OqbQ6hQXw3rFe",
        "uploaded_at": "2026-04-24T15:30:51.583Z"
      },
      {
        "index": 83,
        "vid": "7631404244003720197",
        "video_url": "https://cloudins-cdn.insjay.biz.id/media/r5zBB0J6tDaZulV6a6hrwwMMvRkpCuFISYvI",
        "uploaded_at": "2026-04-24T15:30:51.506Z"
      }
    ]
  }
]